optionsPricingAndGreeks/option.py
optionsPricingAndGreeks/stock.py
optionsPricingAndGreeks/estimator/_estimator.py
optionsPricingAndGreeks/estimator/binomialEstimator.py
optionsPricingAndGreeks/estimator/blackScholesEstimator.py
optionsPricingAndGreeks/estimator/bootstrapEstimator.py
optionsPricingAndGreeks/estimator/greeksEstimator.py
optionsPricingAndGreeks/estimator/monteCarloEstimator.py
optionsPricingAndGreeks/utilities/interval.py
optionsPricingAndGreeks/utilities/optionType.py
optionsPricingAndGreeks/utilities/period.py
optionsPricingAndGreeks/utilities/returnsCalculator.py
optionspricingandgreeks-0.0.6.dist-info/METADATA
optionspricingandgreeks-0.0.6.dist-info/WHEEL
optionspricingandgreeks-0.0.6.dist-info/licenses/LICENSE
optionspricingandgreeks-0.0.6.dist-info/RECORD
