Metadata-Version: 2.1
Name: optionsPricingAndGreeks
Version: 0.0.6
Summary: A package to calculate the price of options and the greeks
Project-URL: Homepage, https://github.com/FilippoTomelleri/optionsPricing-Greeks
Author-email: Filippo Tomelleri <filippo.tomelleri01@gmail.com>
License-File: LICENSE
Classifier: License :: OSI Approved :: MIT License
Classifier: Operating System :: OS Independent
Classifier: Programming Language :: Python :: 3
Requires-Python: >=3.11
